pyarccmder/__init__.py
pyarccmder/cmder.py
pyarccmder/config.py
pyarccmder/exception.py
pyarccmder/file.py
pyarccmder/logger.py
pyarccmder/methods.py
pyarccmder/string.py
pyarccmder/utils.py
pyarccmder-0.0.5.dist-info/METADATA
pyarccmder-0.0.5.dist-info/WHEEL
pyarccmder-0.0.5.dist-info/top_level.txt
pyarccmder-0.0.5.dist-info/RECORD
