Metadata-Version: 2.1
Name: pyarccmder
Version: 0.0.5
Summary: Package permettant d'implementer ses propres commandes avec des fonctionnalités spécifiques
Home-page: UNKNOWN
Author: BILONG NTOUBA Célestin
Author-email: bilongntouba.celestin@gmail.com
License: UNKNOWN
Keywords: python,hivi,pyarccmder,cmder
Platform: UNKNOWN
Requires-Dist: jonschema ; python_version >= "0.0.9123"
Requires-Dist: pytz ; python_version >= "2022.1"
Requires-Dist: asyncio ; python_version >= "3.4.3"
Requires-Dist: typing ; python_version >= "3.7.4.3"
